<?xml version="1.0" encoding="UTF-8"?> 
<formulae> 
	<formula name="isNum"/>
	<formula name="Date"/>
	<formula name="At"/>
	<formula name="CharAt"/>
	<formula name="Compare"/>
	<formula name="Concat"/>
	<formula name="EndsWith"/>
	<formula name="EndsWithIgnoreCase"/>
	<formula name="EqualIgnoreCase"/>
	<formula name="Length"/>
	<formula name="StartsWith"/>
	<formula name="StartsWithIgnoreCase"/>
	<formula name="Substring"/>
	<formula name="Trim"/>
	<formula name="Upper"/>
	<formula name="httpRequest"/>
	<formula name="GetBigDecimal"/>
	<formula name="GetBigInteger"/>
	<formula name="GetBinary"/>
	<formula name="GetBoolean"/>
	<formula name="GetChar"/>
	<formula name="GetDate"/>
	<formula name="GetDouble"/>
	<formula name="GetInt"/>
	<formula name="GetISODate"/>
	<formula name="GetLong"/>
	<formula name="GetObject"/>
	<formula name="GetString"/>

	<formula name="Set"/>
	<formula name="Plus"/>
	<formula name="Minus"/>
	<formula name="Multiply"/>
	<formula name="Divide"/>
	<formula name="Equal"/>
	<formula name="NotEqual"/>
	<formula name="Greater"/>
	<formula name="GreaterEqual"/>
	<formula name="Less"/>
	<formula name="LessEqual"/>
	<formula name="And"/>
	<formula name="Or"/>
	<formula name="Not"/>
	<formula name="UnaryPlus"/>
	<formula name="UnaryMinus"/>
	<formula name="IsNull"/>
	<formula name="IsNotNull"/>
</formulae>